MANIFEST.in
requirements.txt
setup.cfg
setup.py
Juice.egg-info/PKG-INFO
Juice.egg-info/SOURCES.txt
Juice.egg-info/dependency_links.txt
Juice.egg-info/entry_points.txt
Juice.egg-info/not-zip-safe
Juice.egg-info/requires.txt
Juice.egg-info/top_level.txt
juice/__about__.py
juice/__about__.pyc
juice/__init__.py
juice/__init__.pyc
juice/cli.py
juice/cli.pyc
juice/core.py
juice/core.pyc
juice/decorators.py
juice/decorators.pyc
juice/exceptions.py
juice/exceptions.pyc
juice/ext.py
juice/ext.pyc
juice/utils.py
juice/utils.pyc
juice/app-skel/app.py
juice/app-skel/blank
juice/app-skel/config.py
juice/app-skel/juicy.py
juice/app-skel/model.py
juice/app-skel/propel.yml
juice/app-skel/_data/mailer-templates/contact-us.txt
juice/app-skel/_data/mailer-templates/default-template.txt
juice/app-skel/_data/mailer-templates/reset-password.txt
juice/app-skel/_data/mailer-templates/welcome-admin.txt
juice/app-skel/_data/mailer-templates/welcome.txt
juice/app-skel/_data/uploads/empty
juice/app-skel/skel/api/__init__.py
juice/app-skel/skel/api/views.py
juice/app-skel/skel/app/__init__.py
juice/app-skel/skel/app/views.py
juice/app-skel/skel/app/static/assets.yml
juice/app-skel/skel/app/static/css/admin.css
juice/app-skel/skel/app/static/css/style.css
juice/app-skel/skel/app/static/images/blank
juice/app-skel/skel/app/static/js/admin.js
juice/app-skel/skel/app/static/js/app.js
juice/app-skel/skel/app/templates/layout.html
juice/app-skel/skel/app/templates/macros.html
juice/app-skel/skel/app/templates/Index/index.html
juice/extras/__init__.py
juice/extras/__init__.pyc
juice/extras/htmlcompress.py
juice/extras/htmlcompress.pyc
juice/extras/markdown_ext.py
juice/extras/markdown_ext.pyc
juice/plugins/__init__.py
juice/plugins/__init__.pyc
juice/plugins/base/__init__.py
juice/plugins/base/__init__.pyc
juice/plugins/base/static/assets.yml
juice/plugins/base/static/Juice/.bowerrc
juice/plugins/base/static/Juice/bower.json
juice/plugins/base/static/Juice/authomatic/authomatic.js
juice/plugins/base/static/Juice/bootstrap/.bower.json
juice/plugins/base/static/Juice/bootstrap/CHANGELOG.md
juice/plugins/base/static/Juice/bootstrap/Gruntfile.js
juice/plugins/base/static/Juice/bootstrap/LICENSE
